cap_lighthouse_lib/TestDataGenerator.py
cap_lighthouse_lib/__init__.py
cap_lighthouse_lib-0.0.2.dist-info/METADATA
cap_lighthouse_lib-0.0.2.dist-info/WHEEL
cap_lighthouse_lib-0.0.2.dist-info/RECORD
